VintedAPIClient/VintedAPI.py
VintedAPIClient/__init__.py
VintedAPIClient-0.1.1.dist-info/LICENSE
VintedAPIClient-0.1.1.dist-info/METADATA
VintedAPIClient-0.1.1.dist-info/WHEEL
VintedAPIClient-0.1.1.dist-info/top_level.txt
VintedAPIClient-0.1.1.dist-info/RECORD
