Metadata-Version: 2.1
Name: VintedAPIClient
Version: 0.1.1
Summary: Python client for scraping Vinted website
Home-page: https://github.com/giaco8020/VintedScraper
Author: Giaco8020
Classifier: Programming Language :: Python :: 3
Classifier: License :: OSI Approved :: MIT License
Classifier: Operating System :: OS Independent
Requires-Python: >=3.6
License-File: LICENSE
Requires-Dist: requests
Requires-Dist: beautifulsoup4
